airthings/CloudCollector.py
airthings/__init__.py
airthings/main.py
airthings_exporter-0.0.3.dist-info/METADATA
airthings_exporter-0.0.3.dist-info/WHEEL
airthings_exporter-0.0.3.dist-info/entry_points.txt
airthings_exporter-0.0.3.dist-info/top_level.txt
airthings_exporter-0.0.3.dist-info/RECORD
