Metadata-Version: 2.1
Name: airthings-exporter
Version: 0.0.3
Summary: Prometheus exporter for Airthings devices
Project-URL: Homepage, https://github.com/jherrera123/airthings-exporter
Project-URL: Bug Tracker, https://github.com/jherrera123/airthings-exporter/issues
Requires-Dist: prometheus-client (==0.15.0)
Requires-Dist: requests (==2.28.1)
